setup.py
jz/__init__.py
jz.datetime.egg-info/PKG-INFO
jz.datetime.egg-info/SOURCES.txt
jz.datetime.egg-info/dependency_links.txt
jz.datetime.egg-info/namespace_packages.txt
jz.datetime.egg-info/requires.txt
jz.datetime.egg-info/top_level.txt
jz/datetime/__init__.py
jz/datetime/configure.zcml
jz/datetime/jz.datetime-configure.zcml
jz/datetime/readme.txt
jz/datetime/timezone.py
jz/datetime/tests/__init__.py
jz/datetime/tests/test_datetime.py
jz/datetime/tests/test_timezone.py
