Metadata-Version: 1.0
Name: jz.datetime
Version: 0.1
Summary: Date and time helpers.
Home-page: http://www.jellofishi.com/zope
Author: Gabi Shaar
Author-email: gabi@jbox-comp.com
License: GPL
Platform: UNKNOWN
